setup.py
distancesensor/__init__.py
distancesensor/depth.py
distancesensor.egg-info/PKG-INFO
distancesensor.egg-info/SOURCES.txt
distancesensor.egg-info/dependency_links.txt
distancesensor.egg-info/requires.txt
distancesensor.egg-info/top_level.txt