Metadata-Version: 1.0
Name: distancesensor
Version: 1.0
Summary: Ultrasonic sensor values
Home-page: UNKNOWN
Author: Gishnu
Author-email: gishnumohanmg@gmail.com
License: MIT
Platform: UNKNOWN
